ga4gh/gks/metaschema/scripts/jsy2js.py
ga4gh/gks/metaschema/scripts/source2classes.py
ga4gh/gks/metaschema/scripts/source2jsy.py
ga4gh/gks/metaschema/scripts/source2mergedjsy.py
ga4gh/gks/metaschema/scripts/source2splitjs.py
ga4gh/gks/metaschema/scripts/y2t.py
ga4gh/gks/metaschema/tools/source_proc.py
templates/maturity
ga4gh_gks_metaschema-0.3.2.dist-info/LICENSE
ga4gh_gks_metaschema-0.3.2.dist-info/METADATA
ga4gh_gks_metaschema-0.3.2.dist-info/WHEEL
ga4gh_gks_metaschema-0.3.2.dist-info/entry_points.txt
ga4gh_gks_metaschema-0.3.2.dist-info/top_level.txt
ga4gh_gks_metaschema-0.3.2.dist-info/RECORD
