Metadata-Version: 2.2
Name: ga4gh.gks.metaschema
Version: 0.3.2
Summary: GA4GH Genomic Knowledge Standards meta-schema tools
Author-email: Alex Wagner <alex.wagner@nationwidechildrens.org>
License:                                  Apache License
Project-URL: Homepage, https://github.com/ga4gh/gks-metaschema
Project-URL: Documentation, https://github.com/ga4gh/gks-metaschema
Project-URL: Changelog, https://github.com/ga4gh/gks-metaschema/releases
Project-URL: Source, https://github.com/ga4gh/gks-metaschema
Project-URL: Bug Tracker, https://github.com/ga4gh/gks-metaschema/issues
Keywords: bioinformatics,ga4gh,genomics,hgvs,spdi,variation
Classifier: Development Status :: 3 - Alpha
Classifier: Intended Audience :: Developers
Classifier: Intended Audience :: Healthcare Industry
Classifier: Intended Audience :: Science/Research
Classifier: License :: OSI Approved :: Apache Software License
Classifier: Operating System :: OS Independent
Classifier: Programming Language :: Python
Classifier: Programming Language :: Python :: 3
Classifier: Programming Language :: Python :: 3.12
Classifier: Topic :: Scientific/Engineering :: Bio-Informatics
Classifier: Topic :: Scientific/Engineering :: Medical Science Apps.
Requires-Python: >=3.12
License-File: LICENSE
Requires-Dist: pyyaml
Requires-Dist: Jinja2
Provides-Extra: dev
Requires-Dist: pytest; extra == "dev"
Requires-Dist: ruff==0.7.2; extra == "dev"
Requires-Dist: pre-commit~=4.1.0; extra == "dev"
